[
  {  
    "layerName" : "Weather_Temperature",
    "spriteBoxLayout" : [
      {
        "spriteBoxName": "TemperatureTensDigit",
        "spriteRenderMethod" : "CustomHue",
        "x": 32,
        "y": 27,
        "width": 45,
        "height": 69
      },
      {
        "spriteBoxName": "TemperatureOnesDigit",
        "spriteRenderMethod" : "CustomHue",
        "x": 77,
        "y": 27,
        "width": 45,
        "height": 69
      },
      {
        "spriteBoxName": "TemperatureDegreeIndicator",
        "spriteRenderMethod" : "CustomHue",
        "x": 122,
        "y": 27,
        "width": 29,
        "height": 69
      }
    ]
  }
]
